geoips_clavrx/README.md
geoips_clavrx/__init__.py
geoips_clavrx/_version.py
geoips_clavrx/ancillary/ancil_data.py
geoips_clavrx/ancillary/update_dynamic.py
geoips_clavrx/clavrx/hdf4_installer.py
geoips_clavrx/clavrx/hdf5_installer.py
geoips_clavrx/clavrx/himawari_installer.py
geoips_clavrx/clavrx/install_clavrx.py
geoips_clavrx/clavrx/install_utils.py
geoips_clavrx/clavrx/netcdf_installer.py
geoips_clavrx/clavrx/rttov_installer.py
geoips_clavrx/clavrx/user_change_me.py
geoips_clavrx/plugins/__init__.py
geoips_clavrx/plugins/modules/__init__.py
geoips_clavrx/plugins/modules/algorithms/absdiff_cth.py
geoips_clavrx/plugins/modules/colormappers/__init__.py
geoips_clavrx/plugins/modules/colormappers/cmap_IR.py
geoips_clavrx/plugins/modules/colormappers/cmap_cldFraction.py
geoips_clavrx/plugins/modules/colormappers/cmap_cldHeight.py
geoips_clavrx/plugins/modules/colormappers/cmap_cldMask.py
geoips_clavrx/plugins/modules/colormappers/cmap_cldOpd.py
geoips_clavrx/plugins/modules/colormappers/cmap_cldPhase.py
geoips_clavrx/plugins/modules/colormappers/cmap_cldReff.py
geoips_clavrx/plugins/modules/colormappers/cmap_cldTemp.py
geoips_clavrx/plugins/modules/colormappers/cmap_cldType.py
geoips_clavrx/plugins/modules/readers/__init__.py
geoips_clavrx/plugins/modules/readers/clavrx_hdf4.py
geoips_clavrx/plugins/modules/readers/clavrx_netcdf4.py
geoips_clavrx/plugins/yaml/product_defaults/CLAVR-x-Base.yaml
geoips_clavrx/plugins/yaml/product_defaults/Cloud-Height.yaml
geoips_clavrx/plugins/yaml/product_defaults/Temp.yaml
geoips_clavrx/plugins/yaml/products/clavrx.yaml
geoips_clavrx/run_clavrxorb.py
geoips_clavrx/test/test_clavrx.py
geoips_clavrx-1.16.1.dist-info/LICENSE
geoips_clavrx-1.16.1.dist-info/METADATA
geoips_clavrx-1.16.1.dist-info/WHEEL
geoips_clavrx-1.16.1.dist-info/entry_points.txt
geoips_clavrx-1.16.1.dist-info/RECORD
