Metadata-Version: 2.3
Name: geoips_clavrx
Version: 1.16.1
Summary: Geolocated Information Processing System
Keywords: GeoIPS,Poetry
Author: GeoIPS
Author-email: geoips@nrlmry.navy.mil
Maintainer: GeoIPS
Maintainer-email: geoips@nrlmry.navy.mil
Requires-Python: >=3.9
Classifier: Programming Language :: Python :: 3
Classifier: Programming Language :: Python :: 3.9
Classifier: Programming Language :: Python :: 3.10
Classifier: Programming Language :: Python :: 3.11
Classifier: Programming Language :: Python :: 3.12
Classifier: Programming Language :: Python :: 3.13
Provides-Extra: build
Requires-Dist: requests ; extra == "build"
Project-URL: Repository, https://github.com/NRLMMD-GEOIPS/geoips_clavrx
